push_service/__init__.py
push_service/common_pb2.py
push_service/common_pb2_grpc.py
push_service/grpc_client.py
push_service/pushService_pb2.py
push_service/pushService_pb2_grpc.py
longleding_push_service_sdk-0.2.2.dist-info/LICENSE
longleding_push_service_sdk-0.2.2.dist-info/METADATA
longleding_push_service_sdk-0.2.2.dist-info/WHEEL
longleding_push_service_sdk-0.2.2.dist-info/top_level.txt
longleding_push_service_sdk-0.2.2.dist-info/RECORD
