Metadata-Version: 2.1
Name: longleding-push-service-sdk
Version: 0.2.2
Summary: Longleding Push Service SDK
Home-page: https://git.emhub.top/em/push-service
Author: Shi Ran
Author-email: ran.shi@longleding.com
License: UNKNOWN
Platform: UNKNOWN
Classifier: Programming Language :: Python :: 3
Classifier: Topic :: System :: Logging
Requires-Python: >=3.6
